fake_email/__init__.py
fake_email/mail.py
fake_email-2.0.0.dist-info/LICENSE
fake_email-2.0.0.dist-info/METADATA
fake_email-2.0.0.dist-info/WHEEL
fake_email-2.0.0.dist-info/top_level.txt
fake_email-2.0.0.dist-info/RECORD
